{
  "Users": [
    {
      "gender": "male",
      "name": {
        "title": "Mr",
        "first": "Nicolas",
        "last": "Notararigo"
      },
      "location": {
        "street": {
          "number": 1851,
          "name": "W Dallas St"
        },
        "city": "Lyon",
        "state": "",
        "country": "France",
        "postcode": 69007,
        "coordinates": {
          "latitude": "80.5855",
          "longitude": "-39.1018"
        },
        "timezone": {
          "offset": "+3:30",
          "description": "Tehran"
        }
      },
      "email": "nicolas.notararigo@gmail.com",
      "login": {
        "uuid": "5a92e112-d6ca-4f5d-9c7e-72160e6df5f4",
        "username": "Neerfix",
        "password": "qwertyuiop",
        "salt": "1AXO8w2Y",
        "md5": "502ba90c923de3cf43d54fc78d928a4e",
        "sha1": "963ea6bc964b52f7ad5b13d496092e57c8f3ab34",
        "sha256": "273e6ef3153b26b2913ed333c5a6ecfb149b2547e46dccb00efbf45c84a3ed63"
      },
      "birthdate": "1996-12-26",
      "date": "2004-03-30T02:47:54.297Z",
      "phone": "(084)-893-9257",
      "cell": "(655)-044-7913",
      "id": {
        "name": "SSN",
        "value": "1"
      },
      "picture": {
        "large": "https://media.licdn.com/dms/image/C4D03AQE14kxSXRscrQ/profile-displayphoto-shrink_200_200/0?e=1581552000&v=beta&t=MAyM2F90ymVpRuQ2abcu4ASaDOIU7gaO6O38Aup2-mY",
        "medium": "https://media.licdn.com/dms/image/C4D03AQE14kxSXRscrQ/profile-displayphoto-shrink_200_200/0?e=1581552000&v=beta&t=MAyM2F90ymVpRuQ2abcu4ASaDOIU7gaO6O38Aup2-mY",
        "thumbnail": "https://media.licdn.com/dms/image/C4D03AQE14kxSXRscrQ/profile-displayphoto-shrink_200_200/0?e=1581552000&v=beta&t=MAyM2F90ymVpRuQ2abcu4ASaDOIU7gaO6O38Aup2-mY"
      },
      "nat": "FR"
    },
    {
      "gender": "male",
      "name": {
        "title": "Mr",
        "first": "Timmothy",
        "last": "Romero"
      },
      "location": {
        "street": {
          "number": 6786,
          "name": "Karen Dr"
        },
        "city": "Rockhampton",
        "state": "Tasmania",
        "country": "Australia",
        "postcode": 7177,
        "coordinates": {
          "latitude": "8.7436",
          "longitude": "101.8478"
        },
        "timezone": {
          "offset": "-8:00",
          "description": "Pacific Time (US & Canada)"
        }
      },
      "email": "timmothy.romero@example.com",
      "login": {
        "uuid": "a89167cf-2531-4b09-b525-07ec2a6bb49c",
        "username": "orangefrog396",
        "password": "divine",
        "salt": "MV6JN7FR",
        "md5": "71acca13ba3e86a9563464875545d909",
        "sha1": "89f03cce4ea42f9ad250011302b4cdd551a0fcd9",
        "sha256": "15549258af535db4b7ead5117c206bb4d8377c254100e8845ea37452e2b6cc35"
      },
      "dob": {
        "date": "1965-06-06T06:47:28.213Z",
        "age": 54
      },
      "registered": {
        "date": "2015-04-19T09:20:00.891Z",
        "age": 4
      },
      "phone": "04-5444-5906",
      "cell": "0406-049-007",
      "id": {
        "name": "TFN",
        "value": "951676111"
      },
      "picture": {
        "large": "https://randomuser.me/api/portraits/men/53.jpg",
        "medium": "https://randomuser.me/api/portraits/med/men/53.jpg",
        "thumbnail": "https://randomuser.me/api/portraits/thumb/men/53.jpg"
      },
      "nat": "AU"
    },
    {
      "gender": "male",
      "name": {
        "title": "Mr",
        "first": "Gabriel",
        "last": "Jean-Baptiste"
      },
      "location": {
        "street": {
          "number": 3446,
          "name": "15th St"
        },
        "city": "Kingston",
        "state": "Alberta",
        "country": "Canada",
        "postcode": "K4H 3M4",
        "coordinates": {
          "latitude": "77.1557",
          "longitude": "26.2545"
        },
        "timezone": {
          "offset": "-12:00",
          "description": "Eniwetok, Kwajalein"
        }
      },
      "email": "gabriel.jean-baptiste@example.com",
      "login": {
        "uuid": "af8b4855-6b86-4976-b8f0-a0907f10ce81",
        "username": "blueleopard253",
        "password": "karina",
        "salt": "0MUJPaiI",
        "md5": "2051913a8e951b47ab03fa85fe962369",
        "sha1": "90ef74f9430b7f1a8e5fa6cb31fc8e64b994dfe3",
        "sha256": "c67ebcfcbe2a89e79ba6a5809d1ffe16bfb79cd69f4d193315f14531d86aa62c"
      },
      "dob": {
        "date": "1978-09-27T17:28:08.776Z",
        "age": 41
      },
      "registered": {
        "date": "2018-02-07T06:35:52.029Z",
        "age": 1
      },
      "phone": "046-818-0682",
      "cell": "823-215-1592",
      "id": {
        "name": "",
        "value": null
      },
      "picture": {
        "large": "https://randomuser.me/api/portraits/men/48.jpg",
        "medium": "https://randomuser.me/api/portraits/med/men/48.jpg",
        "thumbnail": "https://randomuser.me/api/portraits/thumb/men/48.jpg"
      },
      "nat": "CA"
    },
    {
      "gender": "male",
      "name": {
        "title": "Mr",
        "first": "Ewald",
        "last": "Fiebig"
      },
      "location": {
        "street": {
          "number": 976,
          "name": "Beethovenstraße"
        },
        "city": "Bad Griesbach im Rottal",
        "state": "Hessen",
        "country": "Germany",
        "postcode": 86158,
        "coordinates": {
          "latitude": "19.0754",
          "longitude": "98.2205"
        },
        "timezone": {
          "offset": "-4:00",
          "description": "Atlantic Time (Canada), Caracas, La Paz"
        }
      },
      "email": "ewald.fiebig@example.com",
      "login": {
        "uuid": "a322b205-6050-480f-b9b9-a0288382ae70",
        "username": "silverleopard937",
        "password": "latinas",
        "salt": "dfSuMRDX",
        "md5": "291c8a40b6a097bf8df1f92c0ccae9a6",
        "sha1": "560901a2c6a9e39ae7427c389be7a45a7e68de44",
        "sha256": "4708a5f49236825849b37898b89f113d28ea63d0d9577b665db43fa48ccc1bde"
      },
      "dob": {
        "date": "1968-11-02T06:26:28.418Z",
        "age": 51
      },
      "registered": {
        "date": "2017-07-12T22:41:48.726Z",
        "age": 2
      },
      "phone": "0133-4407362",
      "cell": "0174-0093389",
      "id": {
        "name": "",
        "value": null
      },
      "picture": {
        "large": "https://randomuser.me/api/portraits/men/1.jpg",
        "medium": "https://randomuser.me/api/portraits/med/men/1.jpg",
        "thumbnail": "https://randomuser.me/api/portraits/thumb/men/1.jpg"
      },
      "nat": "DE"
    }
  ],
  "List": [
    {
      "title": "first",
      "isPrivate": false,
      "dateCreated": "2004-03-30T02:47:54.297Z",
      "id": {
        "name": "SSN",
        "value": "1",
        "uuid": "5a92e112-d6ca-4f5d-9c7e-72160e6df5f4"
      },
      "owner_id": "1",
      "Categories": [
        {
          "id": 1,
          "title": "Connaissances de soie",
          "activity": [
            {
              "id": 1,
              "title": "Méditer pendant 30 min",
              "step": [],
              "isDone": true
            }
          ]
        },
        {
          "id": 2,
          "title": "Développement personnel",
          "activity": [
            {
              "id": 2,
              "title": "LIRE UN PREMIER LIVRE DE DÉVELOPPEMENT PERSONNEL.",
              "step": [],
              "isDone": false
            },
            {
              "id": 3,
              "title": "PASSER UN TEST DE PERSONNALITÉ AVANCÉ POUR MIEUX SE CONNAÎTRE.",
              "step": [],
              "isDone": true
            }
          ]
        },
        {
          "id": 3,
          "title": "Développement professionnel",
          "activity": [
            {
              "id": 4,
              "title": "REPRENDRE SES ÉTUDES ET DÉCROCHER UN NOUVEAU DIPLÔME.",
              "step": [
                {
                  "id": 4,
                  "title": "REPRENDRE SES ÉTUDES",
                  "isDone": true
                },
                {
                  "id": 5,
                  "title": "DÉCROCHER UN NOUVEAU DIPLÔME.",
                  "isDone": false
                }
              ],
              "isDone": false
            }
          ]
        },
        {
          "id": 1,
          "title": "Activités sportives",
          "activity": [
            {
              "id": 6,
              "title": "COURIR UN 10KM.",
              "step": [],
              "isDone": true
            },
            {
              "id": 7,
              "title": "COURIR UN SEMI-MARATHON.",
              "step": [],
              "isDone": false
            },
            {
              "id": 8,
              "title": "TERMINER UN MARATHON.",
              "step": [],
              "isDone": false
            }
          ]
        },
        {
          "id": 1,
          "title": "alimentation",
          "activity": [
            {
              "id": 1,
              "title": "PRENDRE UN COURS DE CUISINE",
              "step": [],
              "isDone": false
            },
            {
              "id": 1,
              "title": "FAIRE UNE CURE DE VITAMINES PENDANT UN MOIS.",
              "step": [],
              "isDone": true
            }
          ]
        },
        {
          "id": 1,
          "title": "Relations Humaines",
          "activity": [
            {
              "id": 1,
              "title": "APPRENDRE À BRISER LA GLACE AVEC DES INCONNUS.",
              "step": [],
              "isDone": false
            },
            {
              "id": 1,
              "title": "MAÎTRISER L’ART DE LA CONVERSATION.",
              "step": [],
              "isDone": false
            },
            {
              "id": 1,
              "title": "APPRENDRE À RACONTER DES HISTOIRES (STORYTELLING).",
              "step": [],
              "isDone": false
            },
            {
              "id": 1,
              "title": "SUIVRE UN COACHING VOCAL.",
              "step": [],
              "isDone": false
            }
          ]
        },
        {
          "id": 1,
          "title": "En Couple",
          "activity": [
            {
              "id": 1,
              "title": "Etre heureux en couple",
              "step": [],
              "isDone": false
            },
            {
              "id": 1,
              "title": "Se marier",
              "step": [],
              "isDone": false
            },
            {
              "id": 1,
              "title": "Avoir un enfant",
              "step": [],
              "isDone": true
            }
          ]
        },
        {
          "id": 1,
          "title": "En famille",
          "activity": [
            {
              "id": 1,
              "title": "Méditer en famille pendant 30 min",
              "step": [],
              "isDone": true
            }
          ]
        },
        {
          "id": 1,
          "title": "Voyages",
          "activity": [
            {
              "id": 1,
              "title": "Voir les pyramides",
              "step": [],
              "isDone": false
            },
            {
              "id": 1,
              "title": "Voir la muraille de chine",
              "step": [],
              "isDone": false
            },
            {
              "id": 1,
              "title": "Les chutes du Niagara",
              "step": [],
              "isDone": false
            },
            {
              "id": 1,
              "title": "Voyager à dos de chameaux",
              "step": [],
              "isDone": false
            },
            {
              "id": 1,
              "title": "Voyager en australie",
              "step": [
                {
                  "id": 1,
                  "title": "Voir les kangourous",
                  "isDone": false
                }
              ],
              "isDone": false
            },
            {
              "id": 1,
              "title": "Les aurores boréales",
              "step": [],
              "isDone": false
            }
          ]
        },
        {
          "id": 1,
          "title": "Fiannces",
          "activity": [
            {
              "id": 1,
              "title": "Avoir un compte à 4 chiffres pendant 2 mois consécutifs",
              "step": [
                {
                  "id": 1,
                  "title": "Avoir un compte à 4 chiffres",
                  "isDone": false
                },
                {
                  "id": 1,
                  "title": "Avoir un compte à 4 chiffres pendant 1 mois",
                  "isDone": false
                },
                {
                  "id": 1,
                  "title": "Avoir un compte à 4 chiffres pendant 2 mois",
                  "isDone": false
                }
              ],
              "isDone": false
            }
          ]
        },
        {
          "id": 1,
          "title": "Spiritualités",
          "activity": [
            {
              "id": 1,
              "title": "Méditer pendant 30 min",
              "step": [],
              "isDone": true
            }
          ]
        },
        {
          "id": 1,
          "title": "Contribution",
          "activity": [
            {
              "id": 1,
              "title": "Faire un don",
              "step": [],
              "isDone": true
            }
          ]
        },
        {
          "id": 1,
          "title": "Style de vie",
          "activity": [
            {
              "id": 1,
              "title": "Boire du vin",
              "step": [],
              "isDone": true
            }
          ]
        },
        {
          "id": 1,
          "title": "Juste pour s'amuser",
          "activity": [
            {
              "id": 1,
              "title": "Se faire un tatouage",
              "step": [],
              "isDone": true
            }
          ]
        },
        {
          "id": 1,
          "title": "Apprentissages",
          "activity": [
            {
              "id": 1,
              "title": "Méditer pendant 30 min",
              "step": [],
              "isDone": true
            }
          ]
        },
        {
          "id": 1,
          "title": "Aventures",
          "activity": [
            {
              "id": 1,
              "title": "Méditer pendant 30 min",
              "step": [],
              "isDone": true
            }
          ]
        }
      ]
    }
  ]
}
